{"expireTime":9007200867448766000,"key":"create-remote-file-node-http://localhost:1337/uploads/projects_1_ec9adbe245.jpg","val":{"vary":"Origin","strict-transport-security":"max-age=31536000; includeSubDomains","x-frame-options":"SAMEORIGIN","accept-ranges":"bytes","content-length":"2070366","last-modified":"Mon, 16 Nov 2020 19:36:47 GMT","cache-control":"max-age=0","content-type":"image/jpeg","x-powered-by":"Strapi <strapi.io>","x-response-time":"18ms","date":"Sun, 07 Feb 2021 14:22:55 GMT","connection":"close"}}